__init__.py
abstract_clockify.py
client.py
utils.py
clockify_api_client/__init__.py
clockify_api_client/abstract_clockify.py
clockify_api_client/client.py
clockify_api_client/utils.py
clockify_api_client/factories/__init__.py
clockify_api_client/factories/abstract_factory.py
clockify_api_client/factories/client_factory.py
clockify_api_client/factories/project_factory.py
clockify_api_client/factories/report_factory.py
clockify_api_client/factories/task_factory.py
clockify_api_client/factories/time_entry_factory.py
clockify_api_client/factories/user_factory.py
clockify_api_client/factories/workspace_factory.py
clockify_api_client/models/__init__.py
clockify_api_client/models/client.py
clockify_api_client/models/project.py
clockify_api_client/models/report.py
clockify_api_client/models/task.py
clockify_api_client/models/time_entry.py
clockify_api_client/models/user.py
clockify_api_client/models/workspace.py
clockify_api_client-0.1.0.dist-info/LICENSE
clockify_api_client-0.1.0.dist-info/METADATA
clockify_api_client-0.1.0.dist-info/WHEEL
clockify_api_client-0.1.0.dist-info/top_level.txt
clockify_api_client-0.1.0.dist-info/RECORD
