Metadata-Version: 2.1
Name: clockify-api-client
Version: 0.1.0
Summary: Simple python API client for clockify. Inspired by https://pypi.org/project/clockify/library.
Home-page: https://github.com/eluvia-com/clockify-api-aclient
Author: Michael Bláha
Author-email: michael.blaha@eluvia.com
License: UNKNOWN
Platform: UNKNOWN
Classifier: Programming Language :: Python :: 3
Classifier: License :: OSI Approved :: MIT License
Classifier: Operating System :: OS Independent
Requires-Dist: factory-boy
Requires-Dist: requests
Provides-Extra: dev
Requires-Dist: twine ; extra == 'dev'
